ZhihuWendaRuheKandaiBuJieshou996JiushiChiBuleKuDeLundiao/README.md
ZhihuWendaRuheKandaiBuJieshou996JiushiChiBuleKuDeLundiao/__init__.py
ZhihuWendaRuheKandaiBuJieshou996JiushiChiBuleKuDeLundiao/__main__.py
ZhihuWendaRuheKandaiBuJieshou996JiushiChiBuleKuDeLundiao/file.epub
ZhihuWendaRuheKandaiBuJieshou996JiushiChiBuleKuDeLundiao/index.html
ZhihuWendaRuheKandaiBuJieshou996JiushiChiBuleKuDeLundiao/css/__init__.py
ZhihuWendaRuheKandaiBuJieshou996JiushiChiBuleKuDeLundiao/css/annotations.css
ZhihuWendaRuheKandaiBuJieshou996JiushiChiBuleKuDeLundiao/css/main.css
ZhihuWendaRuheKandaiBuJieshou996JiushiChiBuleKuDeLundiao/css/normalize.css
ZhihuWendaRuheKandaiBuJieshou996JiushiChiBuleKuDeLundiao/css/popup.css
ZhihuWendaRuheKandaiBuJieshou996JiushiChiBuleKuDeLundiao/font/__init__.py
ZhihuWendaRuheKandaiBuJieshou996JiushiChiBuleKuDeLundiao/font/fontello.eot
ZhihuWendaRuheKandaiBuJieshou996JiushiChiBuleKuDeLundiao/font/fontello.svg
ZhihuWendaRuheKandaiBuJieshou996JiushiChiBuleKuDeLundiao/font/fontello.ttf
ZhihuWendaRuheKandaiBuJieshou996JiushiChiBuleKuDeLundiao/font/fontello.woff
ZhihuWendaRuheKandaiBuJieshou996JiushiChiBuleKuDeLundiao/img/__init__.py
ZhihuWendaRuheKandaiBuJieshou996JiushiChiBuleKuDeLundiao/img/annotator-glyph-sprite.png
ZhihuWendaRuheKandaiBuJieshou996JiushiChiBuleKuDeLundiao/img/annotator-icon-sprite.png
ZhihuWendaRuheKandaiBuJieshou996JiushiChiBuleKuDeLundiao/img/apple-touch-icon.png
ZhihuWendaRuheKandaiBuJieshou996JiushiChiBuleKuDeLundiao/img/cancelfullscreen.png
ZhihuWendaRuheKandaiBuJieshou996JiushiChiBuleKuDeLundiao/img/close.png
ZhihuWendaRuheKandaiBuJieshou996JiushiChiBuleKuDeLundiao/img/fullscreen.png
ZhihuWendaRuheKandaiBuJieshou996JiushiChiBuleKuDeLundiao/img/loader.gif
ZhihuWendaRuheKandaiBuJieshou996JiushiChiBuleKuDeLundiao/img/menu-icon.png
ZhihuWendaRuheKandaiBuJieshou996JiushiChiBuleKuDeLundiao/img/save.png
ZhihuWendaRuheKandaiBuJieshou996JiushiChiBuleKuDeLundiao/img/saved.png
zhihu_wenda_ruhe_kandai_bu_jieshou_996_jiushi_chi_bule_ku_de_lundiao-2024.3.5.0.dist-info/METADATA
zhihu_wenda_ruhe_kandai_bu_jieshou_996_jiushi_chi_bule_ku_de_lundiao-2024.3.5.0.dist-info/WHEEL
zhihu_wenda_ruhe_kandai_bu_jieshou_996_jiushi_chi_bule_ku_de_lundiao-2024.3.5.0.dist-info/entry_points.txt
zhihu_wenda_ruhe_kandai_bu_jieshou_996_jiushi_chi_bule_ku_de_lundiao-2024.3.5.0.dist-info/top_level.txt
zhihu_wenda_ruhe_kandai_bu_jieshou_996_jiushi_chi_bule_ku_de_lundiao-2024.3.5.0.dist-info/RECORD
